shift_register/shift_register.v
module shift_register(input d,clk,en,dir,rst,
			output reg [3:0]out);
	always @ (posedge clk)
	if (rst)
		out <=0;
	else begin
		if (en)
			case (dir)
				0:out<={out[2:0],d};
				1:out<={d,out[3:1]};
			endcase
		else
			out<=out;
	end
endmodule

d_ff.v
module dff(clk,reset,d,q);
input clk,reset,d;
output reg q;

always @ (posedge clk)begin
    if(reset)
        q <= 0;
    else
        q <= d;
end
                
endmodule

adder/adder.v
//full adder using data-flow modeling
module adder (
    input a,b,cin,
    output sum,c
);

assign sum = a ^ b ^ cin;
assign c = (a & b) | (b & cin)  | (cin & a) ;

endmodule

top.v
`include "adder/adder.v"
`include "d_ff.v"
`include "shift_register/shift_register.v"

module top(input a, b, clk, rst,
           output [3:0] out);

    wire [3:0] buff_a, buff_b;
    wire cin ;
    wire  cout, buff_out;

    shift_register uus1(.d(a), .clk(clk), .en(1'b1), .dir(1'b1), .rst(rst), .out(buff_a));
    shift_register uus2(.d(b), .clk(clk), .en(1'b1), .dir(1'b1), .rst(rst), .out(buff_b));
    adder uuadr(.a(buff_a[0]), .b(buff_b[0]), .cin(cin), .sum(buff_out), .c(cout));
    dff uud(.clk(clk), .reset(rst), .d(cout), .q(cin));
    shift_register uus3(.d(buff_out), .clk(clk), .en(1'b1), .dir(1'b1), .rst(rst), .out(out));

endmodule

top_tb.v
`timescale 1ns/1ps
`include "top.v"
module top_tb;

    // Inputs
    reg a, b, clk, rst;
    
    // Outputs
    wire [3:0] out;
    
    // Instantiate the Unit Under Test (UUT)
    top uut (
        .a(a),
        .b(b),
        .clk(clk),
        .rst(rst),
        .out(out)
    );
    
    // Initialize clock and reset
    initial begin
        clk = 0;
        rst = 1;
        #10 rst = 0;
    end
    
    // Generate clock
    always #5 clk = ~clk;
    
    // Apply test inputs
    initial begin
        // Test case 1: a = 0101, b = 1010
        a = 1'b0; b = 1'b0;
        #20 a = 1'b0; b = 1'b1;
        #10 a = 1'b0; b = 1'b0;
        #10 a = 1'b1; b = 1'b1;
        #10 a = 1'b0; b = 1'b0;
        
        // Test case 2: a = 1111, b = 1111
        #60 a = 1'b1; b = 1'b1;
        #10 a = 1'b1; b = 1'b1;
        #10 a = 1'b1; b = 1'b1;
        #10 a = 1'b1; b = 1'b1;
        
        // Add more test cases as needed
        
        #100 $finish;
    end
    initial begin
    $dumpfile("top_tb.vcd"); // Specify the desired file name
    $dumpvars(0, top_tb);
	end
    
    // Monitor outputs
    initial begin
        $monitor("a = %b, b = %b, out = %b", a, b, out);
    end

endmodule

top_tb.vcd
$date
	Fri Apr 26 12:29:49 2024
$end
$version
	Icarus Verilog
$end
$timescale
	1ps
$end
$scope module top_tb $end
$var wire 4 ! out [3:0] $end
$var reg 1 " a $end
$var reg 1 # b $end
$var reg 1 $ clk $end
$var reg 1 % rst $end
$scope module uut $end
$var wire 1 " a $end
$var wire 1 # b $end
$var wire 1 $ clk $end
$var wire 1 % rst $end
$var wire 4 & out [3:0] $end
$var wire 1 ' cout $end
$var wire 1 ( cin $end
$var wire 1 ) buff_out $end
$var wire 4 * buff_b [3:0] $end
$var wire 4 + buff_a [3:0] $end
$scope module uuadr $end
$var wire 1 , a $end
$var wire 1 - b $end
$var wire 1 ' c $end
$var wire 1 ) sum $end
$var wire 1 ( cin $end
$upscope $end
$scope module uud $end
$var wire 1 $ clk $end
$var wire 1 ' d $end
$var wire 1 % reset $end
$var reg 1 ( q $end
$upscope $end
$scope module uus1 $end
$var wire 1 $ clk $end
$var wire 1 " d $end
$var wire 1 . dir $end
$var wire 1 / en $end
$var wire 1 % rst $end
$var reg 4 0 out [3:0] $end
$upscope $end
$scope module uus2 $end
$var wire 1 $ clk $end
$var wire 1 # d $end
$var wire 1 1 dir $end
$var wire 1 2 en $end
$var wire 1 % rst $end
$var reg 4 3 out [3:0] $end
$upscope $end
$scope module uus3 $end
$var wire 1 $ clk $end
$var wire 1 ) d $end
$var wire 1 4 dir $end
$var wire 1 5 en $end
$var wire 1 % rst $end
$var reg 4 6 out [3:0] $end
$upscope $end
$upscope $end
$upscope $end
$enddefinitions $end
$comment Show the parameter values. $end
$dumpall
$end
#0
$dumpvars
bx 6
15
14
bx 3
12
11
bx 0
1/
1.
x-
x,
bx +
bx *
x)
x(
x'
bx &
1%
0$
0#
0"
bx !
$end
#5000
0'
0)
0,
0-
b0 +
b0 0
b0 *
b0 3
0(
b0 !
b0 &
b0 6
1$
#10000
0$
0%
#15000
1$
#20000
0$
1#
#25000
b1000 *
b1000 3
1$
#30000
0$
0#
#35000
b100 *
b100 3
1$
#40000
0$
1#
1"
#45000
b1000 +
b1000 0
b1010 *
b1010 3
1$
#50000
0$
0#
0"
#55000
1)
1-
b101 *
b101 3
b100 +
b100 0
1$
#60000
0$
#65000
0)
0-
b10 +
b10 0
b10 *
b10 3
b1000 !
b1000 &
b1000 6
1$
#70000
0$
#75000
1'
1-
1,
b100 !
b100 &
b100 6
b1 *
b1 3
b1 +
b1 0
1$
#80000
0$
#85000
0'
0,
0-
1)
b0 +
b0 0
b0 *
b0 3
1(
b10 !
b10 &
b10 6
1$
#90000
0$
#95000
0)
b1001 !
b1001 &
b1001 6
0(
1$
#100000
0$
#105000
b100 !
b100 &
b100 6
1$
#110000
0$
1#
1"
#115000
b10 !
b10 &
b10 6
b1000 *
b1000 3
b1000 +
b1000 0
1$
#120000
0$
#125000
b1100 +
b1100 0
b1100 *
b1100 3
b1 !
b1 &
b1 6
1$
#130000
0$
#135000
b0 !
b0 &
b0 6
b1110 *
b1110 3
b1110 +
b1110 0
1$
#140000
0$
#145000
1'
1,
1-
b1111 +
b1111 0
b1111 *
b1111 3
1$
#150000
0$
#155000
1)
1(
1$
#160000
0$
#165000
b1000 !
b1000 &
b1000 6
1$
#170000
0$
#175000
b1100 !
b1100 &
b1100 6
1$
#180000
0$
#185000
b1110 !
b1110 &
b1110 6
1$
#190000
0$
#195000
b1111 !
b1111 &
b1111 6
1$
