adder/adder.v
//full adder using data-flow modeling
module adder (
    input a,b,cin,
    output sum,c
);

assign sum = a ^ b ^ cin;
assign c = (a & b) | (b & cin)  | (cin & a) ;

endmodule

adder/adder_tb.v
`timescale 1ns / 1ps
`include "adder.v"
module testbench;

    // Inputs
    reg a, b, cin;

    // Outputs
    wire sum, c;

    // Instantiate the adder module
    adder dut(
        .a(a),
        .b(b),
        .cin(cin),
        .sum(sum),
        .c(c)
    );
        initial begin
            $dumpfile("adder_tb.vcd"); // Specify the desired file name
            $dumpvars(0, testbench);
        end
    // Initial stimulus
    initial begin
        // Initialize inputs
        a = 0;
        b = 0;
        cin = 0;

        // Test case 1
        #10 a = 1; b = 0; cin = 0;
        #10 a = 0; b = 1; cin = 0;
        #10 a = 1; b = 1; cin = 0;
        #10 a = 0; b = 0; cin = 1;
        #10 a = 1; b = 0; cin = 1;
        #10 a = 0; b = 1; cin = 1;
        #10 a = 1; b = 1; cin = 1;

        // End simulation
        #10 $finish;
    end

endmodule

adder/adder_tb.vcd
$date
	Fri Apr 26 12:06:31 2024
$end
$version
	Icarus Verilog
$end
$timescale
	1ps
$end
$scope module testbench $end
$var wire 1 ! sum $end
$var wire 1 " c $end
$var reg 1 # a $end
$var reg 1 $ b $end
$var reg 1 % cin $end
$scope module dut $end
$var wire 1 # a $end
$var wire 1 $ b $end
$var wire 1 " c $end
$var wire 1 % cin $end
$var wire 1 ! sum $end
$upscope $end
$upscope $end
$enddefinitions $end
$comment Show the parameter values. $end
$dumpall
$end
#0
$dumpvars
0%
0$
0#
0"
0!
$end
#10000
1!
1#
#20000
1$
0#
#30000
1"
0!
1#
#40000
0"
1!
1%
0$
0#
#50000
0!
1"
1#
#60000
1"
1$
0#
#70000
1!
1#
