shift_register/shift_register.v
module shift_register(input d,clk,en,dir,rst,
			output reg [3:0]out);
	always @ (posedge clk)
	if (rst)
		out <=0;
	else begin
		if (en)
			case (dir)
				0:out<={out[2:0],d};
				1:out<={d,out[3:1]};
			endcase
		else
			out<=out;
	end
endmodule

shift_register/shift_register_tb.v
`timescale 1ns / 1ps

module testbench;

    // Inputs
    reg d, clk, en, dir, rst;

    // Outputs
    wire [3:0] out;

    // Instantiate the module
    shift_register dut(
        .d(d),
        .clk(clk),
        .en(en),
        .dir(dir),
        .rst(rst),
        .out(out)
    );

    // Clock generation
    always #5 clk = ~clk;

    // Initial stimulus
    initial begin
	$dumpfile("waveform.vcd");
        $dumpvars(0, testbench);
        // Initialize inputs
        d = 0;
        clk = 0;
        en = 1;
        dir = 0;
        rst = 1;

        // Reset
        #10 rst = 0;

        // Test case 1
        #10 d = 1; // Input data
        #10 d = 0; // Input data
        #10 d = 1; // Input data
        #10;      // Wait for shift to happen

        // Test case 2
        en = 0;   // Disable shifting
        #10 d = 0; // Input data
        #10;      // Wait without shifting

        // Test case 3
        en = 1;   // Re-enable shifting
        dir = 1;  // Change direction
        #10 d = 1; // Input data
        #10 d = 0; // Input data
        #10 d = 1; // Input data
        #10;      // Wait for shift to happen

        // End simulation
        #10 $finish;
    end

endmodule

shift_register/waveform.vcd
$date
	Fri Apr 26 11:04:35 2024
$end
$version
	Icarus Verilog
$end
$timescale
	1ps
$end
$scope module testbench $end
$var wire 4 ! out [3:0] $end
$var reg 1 " clk $end
$var reg 1 # d $end
$var reg 1 $ dir $end
$var reg 1 % en $end
$var reg 1 & rst $end
$scope module dut $end
$var wire 1 " clk $end
$var wire 1 # d $end
$var wire 1 $ dir $end
$var wire 1 % en $end
$var wire 1 & rst $end
$var reg 4 ' out [3:0] $end
$upscope $end
$upscope $end
$enddefinitions $end
$comment Show the parameter values. $end
$dumpall
$end
#0
$dumpvars
bx '
1&
1%
0$
0#
0"
bx !
$end
#5000
b0 !
b0 '
1"
#10000
0"
0&
#15000
1"
#20000
0"
1#
#25000
b1 !
b1 '
1"
#30000
0"
0#
#35000
b10 !
b10 '
1"
#40000
0"
1#
#45000
b101 !
b101 '
1"
#50000
0"
0%
#55000
1"
#60000
0"
0#
#65000
1"
#70000
0"
1$
1%
#75000
b10 !
b10 '
1"
#80000
0"
1#
#85000
b1001 !
b1001 '
1"
#90000
0"
0#
#95000
b100 !
b100 '
1"
#100000
0"
1#
#105000
b1010 !
b1010 '
1"
#110000
0"
#115000
b1101 !
b1101 '
1"
